factorytools/__init__.py
factorytools/django.py
factorytools-0.1.0.dist-info/LICENSE
factorytools-0.1.0.dist-info/WHEEL
factorytools-0.1.0.dist-info/METADATA
factorytools-0.1.0.dist-info/RECORD
